{"nodes": [{"id": "c_clerici_c_progetti_test_quality_control_ficep_robserver_ficep_robserver_data_programpoint_cs", "label": "ProgramPoint.cs", "file_type": "code", "source_file": "Ficep.RobServer/Ficep.RobServer.Data/ProgramPoint.cs", "source_location": "L1"}, {"id": "ficep_robserver_data_programpoint_ficep_robserver_data", "label": "Ficep.RobServer.Data", "file_type": "code", "source_file": "Ficep.RobServer/Ficep.RobServer.Data/ProgramPoint.cs", "source_location": "L8"}, {"id": "ficep_robserver_data_programpoint_programpoint", "label": "ProgramPoint", "file_type": "code", "source_file": "Ficep.RobServer/Ficep.RobServer.Data/ProgramPoint.cs", "source_location": "L10"}, {"id": "ipoint", "label": "IPoint", "file_type": "code", "source_file": "", "source_location": ""}, {"id": "iequatable", "label": "IEquatable", "file_type": "code", "source_file": "", "source_location": ""}, {"id": "icloneable", "label": "ICloneable", "file_type": "code", "source_file": "", "source_location": ""}, {"id": "ficep_robserver_data_programpoint_programpoint_arecoordinatesequal", "label": ".AreCoordinatesEqual()", "file_type": "code", "source_file": "Ficep.RobServer/Ficep.RobServer.Data/ProgramPoint.cs", "source_location": "L51"}, {"id": "ficep_robserver_data_programpoint_programpoint_equals", "label": ".Equals()", "file_type": "code", "source_file": "Ficep.RobServer/Ficep.RobServer.Data/ProgramPoint.cs", "source_location": "L55"}, {"id": "ficep_robserver_data_programpoint_programpoint_gethashcode", "label": ".GetHashCode()", "file_type": "code", "source_file": "Ficep.RobServer/Ficep.RobServer.Data/ProgramPoint.cs", "source_location": "L86"}, {"id": "ficep_robserver_data_programpoint_programpoint_clone", "label": ".Clone()", "file_type": "code", "source_file": "Ficep.RobServer/Ficep.RobServer.Data/ProgramPoint.cs", "source_location": "L99"}], "edges": [{"source": "c_clerici_c_progetti_test_quality_control_ficep_robserver_ficep_robserver_data_programpoint_cs", "target": "utils", "relation": "imports", "context": "import", "confidence": "EXTRACTED", "source_file": "Ficep.RobServer/Ficep.RobServer.Data/ProgramPoint.cs", "source_location": "L1", "weight": 1.0}, {"source": "c_clerici_c_progetti_test_quality_control_ficep_robserver_ficep_robserver_data_programpoint_cs", "target": "system", "relation": "imports", "context": "import", "confidence": "EXTRACTED", "source_file": "Ficep.RobServer/Ficep.RobServer.Data/ProgramPoint.cs", "source_location": "L2", "weight": 1.0}, {"source": "c_clerici_c_progetti_test_quality_control_ficep_robserver_ficep_robserver_data_programpoint_cs", "target": "generic", "relation": "imports", "context": "import", "confidence": "EXTRACTED", "source_file": "Ficep.RobServer/Ficep.RobServer.Data/ProgramPoint.cs", "source_location": "L3", "weight": 1.0}, {"source": "c_clerici_c_progetti_test_quality_control_ficep_robserver_ficep_robserver_data_programpoint_cs", "target": "linq", "relation": "imports", "context": "import", "confidence": "EXTRACTED", "source_file": "Ficep.RobServer/Ficep.RobServer.Data/ProgramPoint.cs", "source_location": "L4", "weight": 1.0}, {"source": "c_clerici_c_progetti_test_quality_control_ficep_robserver_ficep_robserver_data_programpoint_cs", "target": "text", "relation": "imports", "context": "import", "confidence": "EXTRACTED", "source_file": "Ficep.RobServer/Ficep.RobServer.Data/ProgramPoint.cs", "source_location": "L5", "weight": 1.0}, {"source": "c_clerici_c_progetti_test_quality_control_ficep_robserver_ficep_robserver_data_programpoint_cs", "target": "tasks", "relation": "imports", "context": "import", "confidence": "EXTRACTED", "source_file": "Ficep.RobServer/Ficep.RobServer.Data/ProgramPoint.cs", "source_location": "L6", "weight": 1.0}, {"source": "c_clerici_c_progetti_test_quality_control_ficep_robserver_ficep_robserver_data_programpoint_cs", "target": "ficep_robserver_data_programpoint_ficep_robserver_data", "relation": "contains", "confidence": "EXTRACTED", "source_file": "Ficep.RobServer/Ficep.RobServer.Data/ProgramPoint.cs", "source_location": "L8", "weight": 1.0}, {"source": "c_clerici_c_progetti_test_quality_control_ficep_robserver_ficep_robserver_data_programpoint_cs", "target": "ficep_robserver_data_programpoint_programpoint", "relation": "contains", "confidence": "EXTRACTED", "source_file": "Ficep.RobServer/Ficep.RobServer.Data/ProgramPoint.cs", "source_location": "L10", "weight": 1.0}, {"source": "ficep_robserver_data_programpoint_programpoint", "target": "ipoint", "relation": "implements", "confidence": "EXTRACTED", "source_file": "Ficep.RobServer/Ficep.RobServer.Data/ProgramPoint.cs", "source_location": "L10", "weight": 1.0}, {"source": "ficep_robserver_data_programpoint_programpoint", "target": "iequatable", "relation": "implements", "confidence": "EXTRACTED", "source_file": "Ficep.RobServer/Ficep.RobServer.Data/ProgramPoint.cs", "source_location": "L10", "weight": 1.0}, {"source": "ficep_robserver_data_programpoint_programpoint", "target": "ficep_robserver_data_programpoint_programpoint", "relation": "references", "confidence": "EXTRACTED", "source_file": "Ficep.RobServer/Ficep.RobServer.Data/ProgramPoint.cs", "source_location": "L10", "weight": 1.0, "context": "generic_arg"}, {"source": "ficep_robserver_data_programpoint_programpoint", "target": "icloneable", "relation": "implements", "confidence": "EXTRACTED", "source_file": "Ficep.RobServer/Ficep.RobServer.Data/ProgramPoint.cs", "source_location": "L10", "weight": 1.0}, {"source": "ficep_robserver_data_programpoint_programpoint", "target": "ficep_robserver_data_programpoint_programpoint_arecoordinatesequal", "relation": "method", "confidence": "EXTRACTED", "source_file": "Ficep.RobServer/Ficep.RobServer.Data/ProgramPoint.cs", "source_location": "L51", "weight": 1.0}, {"source": "ficep_robserver_data_programpoint_programpoint_arecoordinatesequal", "target": "ficep_robserver_data_programpoint_programpoint", "relation": "references", "confidence": "EXTRACTED", "source_file": "Ficep.RobServer/Ficep.RobServer.Data/ProgramPoint.cs", "source_location": "L51", "weight": 1.0, "context": "parameter_type"}, {"source": "ficep_robserver_data_programpoint_programpoint", "target": "ficep_robserver_data_programpoint_programpoint_equals", "relation": "method", "confidence": "EXTRACTED", "source_file": "Ficep.RobServer/Ficep.RobServer.Data/ProgramPoint.cs", "source_location": "L55", "weight": 1.0}, {"source": "ficep_robserver_data_programpoint_programpoint", "target": "ficep_robserver_data_programpoint_programpoint_equals", "relation": "method", "confidence": "EXTRACTED", "source_file": "Ficep.RobServer/Ficep.RobServer.Data/ProgramPoint.cs", "source_location": "L64", "weight": 1.0}, {"source": "ficep_robserver_data_programpoint_programpoint_equals", "target": "ficep_robserver_data_programpoint_programpoint", "relation": "references", "confidence": "EXTRACTED", "source_file": "Ficep.RobServer/Ficep.RobServer.Data/ProgramPoint.cs", "source_location": "L64", "weight": 1.0, "context": "parameter_type"}, {"source": "ficep_robserver_data_programpoint_programpoint", "target": "ficep_robserver_data_programpoint_programpoint_equals", "relation": "method", "confidence": "EXTRACTED", "source_file": "Ficep.RobServer/Ficep.RobServer.Data/ProgramPoint.cs", "source_location": "L74", "weight": 1.0}, {"source": "ficep_robserver_data_programpoint_programpoint_equals", "target": "ficep_robserver_data_programpoint_programpoint", "relation": "references", "confidence": "EXTRACTED", "source_file": "Ficep.RobServer/Ficep.RobServer.Data/ProgramPoint.cs", "source_location": "L74", "weight": 1.0, "context": "parameter_type"}, {"source": "ficep_robserver_data_programpoint_programpoint", "target": "ficep_robserver_data_programpoint_programpoint_gethashcode", "relation": "method", "confidence": "EXTRACTED", "source_file": "Ficep.RobServer/Ficep.RobServer.Data/ProgramPoint.cs", "source_location": "L86", "weight": 1.0}, {"source": "ficep_robserver_data_programpoint_programpoint", "target": "ficep_robserver_data_programpoint_programpoint_clone", "relation": "method", "confidence": "EXTRACTED", "source_file": "Ficep.RobServer/Ficep.RobServer.Data/ProgramPoint.cs", "source_location": "L99", "weight": 1.0}], "raw_calls": [{"caller_nid": "ficep_robserver_data_programpoint_programpoint_equals", "callee": "GetType", "is_member_call": true, "source_file": "C:\\Clerici\\C#\\Progetti\\Test\\Quality control\\Ficep.RobServer\\Ficep.RobServer.Data\\ProgramPoint.cs", "source_location": "L59", "receiver": null}, {"caller_nid": "ficep_robserver_data_programpoint_programpoint_equals", "callee": "GetType", "is_member_call": true, "source_file": "C:\\Clerici\\C#\\Progetti\\Test\\Quality control\\Ficep.RobServer\\Ficep.RobServer.Data\\ProgramPoint.cs", "source_location": "L59", "receiver": null}, {"caller_nid": "ficep_robserver_data_programpoint_programpoint_equals", "callee": "ReferenceEquals", "is_member_call": false, "source_file": "C:\\Clerici\\C#\\Progetti\\Test\\Quality control\\Ficep.RobServer\\Ficep.RobServer.Data\\ProgramPoint.cs", "source_location": "L68", "receiver": null}, {"caller_nid": "ficep_robserver_data_programpoint_programpoint_equals", "callee": "IsEqualTo", "is_member_call": true, "source_file": "C:\\Clerici\\C#\\Progetti\\Test\\Quality control\\Ficep.RobServer\\Ficep.RobServer.Data\\ProgramPoint.cs", "source_location": "L70", "receiver": null}, {"caller_nid": "ficep_robserver_data_programpoint_programpoint_equals", "callee": "IsEqualTo", "is_member_call": true, "source_file": "C:\\Clerici\\C#\\Progetti\\Test\\Quality control\\Ficep.RobServer\\Ficep.RobServer.Data\\ProgramPoint.cs", "source_location": "L70", "receiver": null}, {"caller_nid": "ficep_robserver_data_programpoint_programpoint_equals", "callee": "IsEqualTo", "is_member_call": true, "source_file": "C:\\Clerici\\C#\\Progetti\\Test\\Quality control\\Ficep.RobServer\\Ficep.RobServer.Data\\ProgramPoint.cs", "source_location": "L70", "receiver": null}, {"caller_nid": "ficep_robserver_data_programpoint_programpoint_equals", "callee": "IsEqualTo", "is_member_call": true, "source_file": "C:\\Clerici\\C#\\Progetti\\Test\\Quality control\\Ficep.RobServer\\Ficep.RobServer.Data\\ProgramPoint.cs", "source_location": "L71", "receiver": null}, {"caller_nid": "ficep_robserver_data_programpoint_programpoint_equals", "callee": "ReferenceEquals", "is_member_call": false, "source_file": "C:\\Clerici\\C#\\Progetti\\Test\\Quality control\\Ficep.RobServer\\Ficep.RobServer.Data\\ProgramPoint.cs", "source_location": "L79", "receiver": null}, {"caller_nid": "ficep_robserver_data_programpoint_programpoint_equals", "callee": "IsEqualTo", "is_member_call": true, "source_file": "C:\\Clerici\\C#\\Progetti\\Test\\Quality control\\Ficep.RobServer\\Ficep.RobServer.Data\\ProgramPoint.cs", "source_location": "L81", "receiver": null}, {"caller_nid": "ficep_robserver_data_programpoint_programpoint_equals", "callee": "IsEqualTo", "is_member_call": true, "source_file": "C:\\Clerici\\C#\\Progetti\\Test\\Quality control\\Ficep.RobServer\\Ficep.RobServer.Data\\ProgramPoint.cs", "source_location": "L81", "receiver": null}, {"caller_nid": "ficep_robserver_data_programpoint_programpoint_equals", "callee": "IsEqualTo", "is_member_call": true, "source_file": "C:\\Clerici\\C#\\Progetti\\Test\\Quality control\\Ficep.RobServer\\Ficep.RobServer.Data\\ProgramPoint.cs", "source_location": "L81", "receiver": null}, {"caller_nid": "ficep_robserver_data_programpoint_programpoint_equals", "callee": "IsEqualTo", "is_member_call": true, "source_file": "C:\\Clerici\\C#\\Progetti\\Test\\Quality control\\Ficep.RobServer\\Ficep.RobServer.Data\\ProgramPoint.cs", "source_location": "L82", "receiver": null}]}