{"nodes": [{"id": "c_clerici_c_progetti_test_quality_control_ficep_robserver_ficep_robserver_macroparser_data_cs", "label": "Data.cs", "file_type": "code", "source_file": "Ficep.RobServer/Ficep.RobServer.MacroParser/Data.cs", "source_location": "L1"}, {"id": "ficep_robserver_macroparser_data_ficep_robserver_macroparser", "label": "Ficep.RobServer.MacroParser", "file_type": "code", "source_file": "Ficep.RobServer/Ficep.RobServer.MacroParser/Data.cs", "source_location": "L8"}, {"id": "ficep_robserver_macroparser_data_mat", "label": "MAT", "file_type": "code", "source_file": "Ficep.RobServer/Ficep.RobServer.MacroParser/Data.cs", "source_location": "L10"}, {"id": "isection", "label": "ISection", "file_type": "code", "source_file": "", "source_location": ""}, {"id": "string", "label": "string", "file_type": "code", "source_file": "Ficep.RobServer/Ficep.RobServer.MacroParser/Data.cs", "source_location": "L14"}, {"id": "ficep_robserver_macroparser_data_mat_createdatalines", "label": ".CreateDataLines()", "file_type": "code", "source_file": "Ficep.RobServer/Ficep.RobServer.MacroParser/Data.cs", "source_location": "L39"}, {"id": "ficep_robserver_macroparser_data_pcs", "label": "PCS", "file_type": "code", "source_file": "Ficep.RobServer/Ficep.RobServer.MacroParser/Data.cs", "source_location": "L85"}, {"id": "ficep_robserver_macroparser_data_pcs_createdatalines", "label": ".CreateDataLines()", "file_type": "code", "source_file": "Ficep.RobServer/Ficep.RobServer.MacroParser/Data.cs", "source_location": "L116"}, {"id": "ficep_robserver_macroparser_data_prf", "label": "PRF", "file_type": "code", "source_file": "Ficep.RobServer/Ficep.RobServer.MacroParser/Data.cs", "source_location": "L201"}, {"id": "ficep_robserver_macroparser_data_prf_createdatalines", "label": ".CreateDataLines()", "file_type": "code", "source_file": "Ficep.RobServer/Ficep.RobServer.MacroParser/Data.cs", "source_location": "L233"}, {"id": "ficep_robserver_macroparser_data_copeline", "label": "CopeLine", "file_type": "code", "source_file": "Ficep.RobServer/Ficep.RobServer.MacroParser/Data.cs", "source_location": "L280"}, {"id": "idataline", "label": "IDataLine", "file_type": "code", "source_file": "", "source_location": ""}, {"id": "ficep_robserver_macroparser_data_headline", "label": "HeadLine", "file_type": "code", "source_file": "Ficep.RobServer/Ficep.RobServer.MacroParser/Data.cs", "source_location": "L291"}, {"id": "ficep_robserver_macroparser_data_holeline", "label": "HoleLine", "file_type": "code", "source_file": "Ficep.RobServer/Ficep.RobServer.MacroParser/Data.cs", "source_location": "L302"}, {"id": "ficep_robserver_macroparser_data_markline", "label": "MarkLine", "file_type": "code", "source_file": "Ficep.RobServer/Ficep.RobServer.MacroParser/Data.cs", "source_location": "L313"}, {"id": "ficep_robserver_macroparser_data_leadline", "label": "LeadLine", "file_type": "code", "source_file": "Ficep.RobServer/Ficep.RobServer.MacroParser/Data.cs", "source_location": "L324"}, {"id": "ficep_robserver_macroparser_data_cutline", "label": "CutLine", "file_type": "code", "source_file": "Ficep.RobServer/Ficep.RobServer.MacroParser/Data.cs", "source_location": "L335"}, {"id": "ficep_robserver_macroparser_data_prfline", "label": "PrfLine", "file_type": "code", "source_file": "Ficep.RobServer/Ficep.RobServer.MacroParser/Data.cs", "source_location": "L346"}, {"id": "ficep_robserver_macroparser_data_matline", "label": "MatLine", "file_type": "code", "source_file": "Ficep.RobServer/Ficep.RobServer.MacroParser/Data.cs", "source_location": "L357"}, {"id": "ficep_robserver_macroparser_data_isection", "label": "ISection", "file_type": "code", "source_file": "Ficep.RobServer/Ficep.RobServer.MacroParser/Data.cs", "source_location": "L373"}, {"id": "ficep_robserver_macroparser_data_idataline", "label": "IDataLine", "file_type": "code", "source_file": "Ficep.RobServer/Ficep.RobServer.MacroParser/Data.cs", "source_location": "L380"}], "edges": [{"source": "c_clerici_c_progetti_test_quality_control_ficep_robserver_ficep_robserver_macroparser_data_cs", "target": "system", "relation": "imports", "context": "import", "confidence": "EXTRACTED", "source_file": "Ficep.RobServer/Ficep.RobServer.MacroParser/Data.cs", "source_location": "L1", "weight": 1.0}, {"source": "c_clerici_c_progetti_test_quality_control_ficep_robserver_ficep_robserver_macroparser_data_cs", "target": "generic", "relation": "imports", "context": "import", "confidence": "EXTRACTED", "source_file": "Ficep.RobServer/Ficep.RobServer.MacroParser/Data.cs", "source_location": "L2", "weight": 1.0}, {"source": "c_clerici_c_progetti_test_quality_control_ficep_robserver_ficep_robserver_macroparser_data_cs", "target": "linq", "relation": "imports", "context": "import", "confidence": "EXTRACTED", "source_file": "Ficep.RobServer/Ficep.RobServer.MacroParser/Data.cs", "source_location": "L3", "weight": 1.0}, {"source": "c_clerici_c_progetti_test_quality_control_ficep_robserver_ficep_robserver_macroparser_data_cs", "target": "text", "relation": "imports", "context": "import", "confidence": "EXTRACTED", "source_file": "Ficep.RobServer/Ficep.RobServer.MacroParser/Data.cs", "source_location": "L4", "weight": 1.0}, {"source": "c_clerici_c_progetti_test_quality_control_ficep_robserver_ficep_robserver_macroparser_data_cs", "target": "regularexpressions", "relation": "imports", "context": "import", "confidence": "EXTRACTED", "source_file": "Ficep.RobServer/Ficep.RobServer.MacroParser/Data.cs", "source_location": "L5", "weight": 1.0}, {"source": "c_clerici_c_progetti_test_quality_control_ficep_robserver_ficep_robserver_macroparser_data_cs", "target": "tasks", "relation": "imports", "context": "import", "confidence": "EXTRACTED", "source_file": "Ficep.RobServer/Ficep.RobServer.MacroParser/Data.cs", "source_location": "L6", "weight": 1.0}, {"source": "c_clerici_c_progetti_test_quality_control_ficep_robserver_ficep_robserver_macroparser_data_cs", "target": "ficep_robserver_macroparser_data_ficep_robserver_macroparser", "relation": "contains", "confidence": "EXTRACTED", "source_file": "Ficep.RobServer/Ficep.RobServer.MacroParser/Data.cs", "source_location": "L8", "weight": 1.0}, {"source": "c_clerici_c_progetti_test_quality_control_ficep_robserver_ficep_robserver_macroparser_data_cs", "target": "ficep_robserver_macroparser_data_mat", "relation": "contains", "confidence": "EXTRACTED", "source_file": "Ficep.RobServer/Ficep.RobServer.MacroParser/Data.cs", "source_location": "L10", "weight": 1.0}, {"source": "ficep_robserver_macroparser_data_mat", "target": "isection", "relation": "implements", "confidence": "EXTRACTED", "source_file": "Ficep.RobServer/Ficep.RobServer.MacroParser/Data.cs", "source_location": "L10", "weight": 1.0}, {"source": "ficep_robserver_macroparser_data_mat", "target": "string", "relation": "references", "confidence": "EXTRACTED", "source_file": "Ficep.RobServer/Ficep.RobServer.MacroParser/Data.cs", "source_location": "L14", "weight": 1.0, "context": "field"}, {"source": "ficep_robserver_macroparser_data_mat", "target": "string", "relation": "references", "confidence": "EXTRACTED", "source_file": "Ficep.RobServer/Ficep.RobServer.MacroParser/Data.cs", "source_location": "L15", "weight": 1.0, "context": "field"}, {"source": "ficep_robserver_macroparser_data_mat", "target": "ficep_robserver_macroparser_data_mat_createdatalines", "relation": "method", "confidence": "EXTRACTED", "source_file": "Ficep.RobServer/Ficep.RobServer.MacroParser/Data.cs", "source_location": "L39", "weight": 1.0}, {"source": "c_clerici_c_progetti_test_quality_control_ficep_robserver_ficep_robserver_macroparser_data_cs", "target": "ficep_robserver_macroparser_data_pcs", "relation": "contains", "confidence": "EXTRACTED", "source_file": "Ficep.RobServer/Ficep.RobServer.MacroParser/Data.cs", "source_location": "L85", "weight": 1.0}, {"source": "ficep_robserver_macroparser_data_pcs", "target": "isection", "relation": "implements", "confidence": "EXTRACTED", "source_file": "Ficep.RobServer/Ficep.RobServer.MacroParser/Data.cs", "source_location": "L85", "weight": 1.0}, {"source": "ficep_robserver_macroparser_data_pcs", "target": "string", "relation": "references", "confidence": "EXTRACTED", "source_file": "Ficep.RobServer/Ficep.RobServer.MacroParser/Data.cs", "source_location": "L89", "weight": 1.0, "context": "field"}, {"source": "ficep_robserver_macroparser_data_pcs", "target": "string", "relation": "references", "confidence": "EXTRACTED", "source_file": "Ficep.RobServer/Ficep.RobServer.MacroParser/Data.cs", "source_location": "L90", "weight": 1.0, "context": "field"}, {"source": "ficep_robserver_macroparser_data_pcs", "target": "ficep_robserver_macroparser_data_pcs_createdatalines", "relation": "method", "confidence": "EXTRACTED", "source_file": "Ficep.RobServer/Ficep.RobServer.MacroParser/Data.cs", "source_location": "L116", "weight": 1.0}, {"source": "c_clerici_c_progetti_test_quality_control_ficep_robserver_ficep_robserver_macroparser_data_cs", "target": "ficep_robserver_macroparser_data_prf", "relation": "contains", "confidence": "EXTRACTED", "source_file": "Ficep.RobServer/Ficep.RobServer.MacroParser/Data.cs", "source_location": "L201", "weight": 1.0}, {"source": "ficep_robserver_macroparser_data_prf", "target": "isection", "relation": "implements", "confidence": "EXTRACTED", "source_file": "Ficep.RobServer/Ficep.RobServer.MacroParser/Data.cs", "source_location": "L201", "weight": 1.0}, {"source": "ficep_robserver_macroparser_data_prf", "target": "string", "relation": "references", "confidence": "EXTRACTED", "source_file": "Ficep.RobServer/Ficep.RobServer.MacroParser/Data.cs", "source_location": "L205", "weight": 1.0, "context": "field"}, {"source": "ficep_robserver_macroparser_data_prf", "target": "string", "relation": "references", "confidence": "EXTRACTED", "source_file": "Ficep.RobServer/Ficep.RobServer.MacroParser/Data.cs", "source_location": "L206", "weight": 1.0, "context": "field"}, {"source": "ficep_robserver_macroparser_data_prf", "target": "ficep_robserver_macroparser_data_prf_createdatalines", "relation": "method", "confidence": "EXTRACTED", "source_file": "Ficep.RobServer/Ficep.RobServer.MacroParser/Data.cs", "source_location": "L233", "weight": 1.0}, {"source": "c_clerici_c_progetti_test_quality_control_ficep_robserver_ficep_robserver_macroparser_data_cs", "target": "ficep_robserver_macroparser_data_copeline", "relation": "contains", "confidence": "EXTRACTED", "source_file": "Ficep.RobServer/Ficep.RobServer.MacroParser/Data.cs", "source_location": "L280", "weight": 1.0}, {"source": "ficep_robserver_macroparser_data_copeline", "target": "idataline", "relation": "implements", "confidence": "EXTRACTED", "source_file": "Ficep.RobServer/Ficep.RobServer.MacroParser/Data.cs", "source_location": "L280", "weight": 1.0}, {"source": "c_clerici_c_progetti_test_quality_control_ficep_robserver_ficep_robserver_macroparser_data_cs", "target": "ficep_robserver_macroparser_data_headline", "relation": "contains", "confidence": "EXTRACTED", "source_file": "Ficep.RobServer/Ficep.RobServer.MacroParser/Data.cs", "source_location": "L291", "weight": 1.0}, {"source": "ficep_robserver_macroparser_data_headline", "target": "idataline", "relation": "implements", "confidence": "EXTRACTED", "source_file": "Ficep.RobServer/Ficep.RobServer.MacroParser/Data.cs", "source_location": "L291", "weight": 1.0}, {"source": "c_clerici_c_progetti_test_quality_control_ficep_robserver_ficep_robserver_macroparser_data_cs", "target": "ficep_robserver_macroparser_data_holeline", "relation": "contains", "confidence": "EXTRACTED", "source_file": "Ficep.RobServer/Ficep.RobServer.MacroParser/Data.cs", "source_location": "L302", "weight": 1.0}, {"source": "ficep_robserver_macroparser_data_holeline", "target": "idataline", "relation": "implements", "confidence": "EXTRACTED", "source_file": "Ficep.RobServer/Ficep.RobServer.MacroParser/Data.cs", "source_location": "L302", "weight": 1.0}, {"source": "c_clerici_c_progetti_test_quality_control_ficep_robserver_ficep_robserver_macroparser_data_cs", "target": "ficep_robserver_macroparser_data_markline", "relation": "contains", "confidence": "EXTRACTED", "source_file": "Ficep.RobServer/Ficep.RobServer.MacroParser/Data.cs", "source_location": "L313", "weight": 1.0}, {"source": "ficep_robserver_macroparser_data_markline", "target": "idataline", "relation": "implements", "confidence": "EXTRACTED", "source_file": "Ficep.RobServer/Ficep.RobServer.MacroParser/Data.cs", "source_location": "L313", "weight": 1.0}, {"source": "c_clerici_c_progetti_test_quality_control_ficep_robserver_ficep_robserver_macroparser_data_cs", "target": "ficep_robserver_macroparser_data_leadline", "relation": "contains", "confidence": "EXTRACTED", "source_file": "Ficep.RobServer/Ficep.RobServer.MacroParser/Data.cs", "source_location": "L324", "weight": 1.0}, {"source": "ficep_robserver_macroparser_data_leadline", "target": "idataline", "relation": "implements", "confidence": "EXTRACTED", "source_file": "Ficep.RobServer/Ficep.RobServer.MacroParser/Data.cs", "source_location": "L324", "weight": 1.0}, {"source": "c_clerici_c_progetti_test_quality_control_ficep_robserver_ficep_robserver_macroparser_data_cs", "target": "ficep_robserver_macroparser_data_cutline", "relation": "contains", "confidence": "EXTRACTED", "source_file": "Ficep.RobServer/Ficep.RobServer.MacroParser/Data.cs", "source_location": "L335", "weight": 1.0}, {"source": "ficep_robserver_macroparser_data_cutline", "target": "idataline", "relation": "implements", "confidence": "EXTRACTED", "source_file": "Ficep.RobServer/Ficep.RobServer.MacroParser/Data.cs", "source_location": "L335", "weight": 1.0}, {"source": "c_clerici_c_progetti_test_quality_control_ficep_robserver_ficep_robserver_macroparser_data_cs", "target": "ficep_robserver_macroparser_data_prfline", "relation": "contains", "confidence": "EXTRACTED", "source_file": "Ficep.RobServer/Ficep.RobServer.MacroParser/Data.cs", "source_location": "L346", "weight": 1.0}, {"source": "ficep_robserver_macroparser_data_prfline", "target": "idataline", "relation": "implements", "confidence": "EXTRACTED", "source_file": "Ficep.RobServer/Ficep.RobServer.MacroParser/Data.cs", "source_location": "L346", "weight": 1.0}, {"source": "c_clerici_c_progetti_test_quality_control_ficep_robserver_ficep_robserver_macroparser_data_cs", "target": "ficep_robserver_macroparser_data_matline", "relation": "contains", "confidence": "EXTRACTED", "source_file": "Ficep.RobServer/Ficep.RobServer.MacroParser/Data.cs", "source_location": "L357", "weight": 1.0}, {"source": "ficep_robserver_macroparser_data_matline", "target": "idataline", "relation": "implements", "confidence": "EXTRACTED", "source_file": "Ficep.RobServer/Ficep.RobServer.MacroParser/Data.cs", "source_location": "L357", "weight": 1.0}, {"source": "c_clerici_c_progetti_test_quality_control_ficep_robserver_ficep_robserver_macroparser_data_cs", "target": "ficep_robserver_macroparser_data_isection", "relation": "contains", "confidence": "EXTRACTED", "source_file": "Ficep.RobServer/Ficep.RobServer.MacroParser/Data.cs", "source_location": "L373", "weight": 1.0}, {"source": "c_clerici_c_progetti_test_quality_control_ficep_robserver_ficep_robserver_macroparser_data_cs", "target": "ficep_robserver_macroparser_data_idataline", "relation": "contains", "confidence": "EXTRACTED", "source_file": "Ficep.RobServer/Ficep.RobServer.MacroParser/Data.cs", "source_location": "L380", "weight": 1.0}], "raw_calls": [{"caller_nid": "ficep_robserver_macroparser_data_mat_createdatalines", "callee": "Match", "is_member_call": true, "source_file": "C:\\Clerici\\C#\\Progetti\\Test\\Quality control\\Ficep.RobServer\\Ficep.RobServer.MacroParser\\Data.cs", "source_location": "L50", "receiver": null}, {"caller_nid": "ficep_robserver_macroparser_data_mat_createdatalines", "callee": "First", "is_member_call": true, "source_file": "C:\\Clerici\\C#\\Progetti\\Test\\Quality control\\Ficep.RobServer\\Ficep.RobServer.MacroParser\\Data.cs", "source_location": "L50", "receiver": null}, {"caller_nid": "ficep_robserver_macroparser_data_mat_createdatalines", "callee": "Split", "is_member_call": true, "source_file": "C:\\Clerici\\C#\\Progetti\\Test\\Quality control\\Ficep.RobServer\\Ficep.RobServer.MacroParser\\Data.cs", "source_location": "L50", "receiver": null}, {"caller_nid": "ficep_robserver_macroparser_data_mat_createdatalines", "callee": "IsMatch", "is_member_call": true, "source_file": "C:\\Clerici\\C#\\Progetti\\Test\\Quality control\\Ficep.RobServer\\Ficep.RobServer.MacroParser\\Data.cs", "source_location": "L54", "receiver": null}, {"caller_nid": "ficep_robserver_macroparser_data_mat_createdatalines", "callee": "First", "is_member_call": true, "source_file": "C:\\Clerici\\C#\\Progetti\\Test\\Quality control\\Ficep.RobServer\\Ficep.RobServer.MacroParser\\Data.cs", "source_location": "L54", "receiver": null}, {"caller_nid": "ficep_robserver_macroparser_data_mat_createdatalines", "callee": "Split", "is_member_call": true, "source_file": "C:\\Clerici\\C#\\Progetti\\Test\\Quality control\\Ficep.RobServer\\Ficep.RobServer.MacroParser\\Data.cs", "source_location": "L54", "receiver": null}, {"caller_nid": "ficep_robserver_macroparser_data_mat_createdatalines", "callee": "Add", "is_member_call": true, "source_file": "C:\\Clerici\\C#\\Progetti\\Test\\Quality control\\Ficep.RobServer\\Ficep.RobServer.MacroParser\\Data.cs", "source_location": "L57", "receiver": null}, {"caller_nid": "ficep_robserver_macroparser_data_mat_createdatalines", "callee": "IsMatch", "is_member_call": true, "source_file": "C:\\Clerici\\C#\\Progetti\\Test\\Quality control\\Ficep.RobServer\\Ficep.RobServer.MacroParser\\Data.cs", "source_location": "L66", "receiver": null}, {"caller_nid": "ficep_robserver_macroparser_data_mat_createdatalines", "callee": "First", "is_member_call": true, "source_file": "C:\\Clerici\\C#\\Progetti\\Test\\Quality control\\Ficep.RobServer\\Ficep.RobServer.MacroParser\\Data.cs", "source_location": "L66", "receiver": null}, {"caller_nid": "ficep_robserver_macroparser_data_mat_createdatalines", "callee": "Split", "is_member_call": true, "source_file": "C:\\Clerici\\C#\\Progetti\\Test\\Quality control\\Ficep.RobServer\\Ficep.RobServer.MacroParser\\Data.cs", "source_location": "L66", "receiver": null}, {"caller_nid": "ficep_robserver_macroparser_data_mat_createdatalines", "callee": "Add", "is_member_call": true, "source_file": "C:\\Clerici\\C#\\Progetti\\Test\\Quality control\\Ficep.RobServer\\Ficep.RobServer.MacroParser\\Data.cs", "source_location": "L69", "receiver": null}, {"caller_nid": "ficep_robserver_macroparser_data_mat_createdatalines", "callee": "Match", "is_member_call": true, "source_file": "C:\\Clerici\\C#\\Progetti\\Test\\Quality control\\Ficep.RobServer\\Ficep.RobServer.MacroParser\\Data.cs", "source_location": "L75", "receiver": null}, {"caller_nid": "ficep_robserver_macroparser_data_mat_createdatalines", "callee": "First", "is_member_call": true, "source_file": "C:\\Clerici\\C#\\Progetti\\Test\\Quality control\\Ficep.RobServer\\Ficep.RobServer.MacroParser\\Data.cs", "source_location": "L75", "receiver": null}, {"caller_nid": "ficep_robserver_macroparser_data_mat_createdatalines", "callee": "Split", "is_member_call": true, "source_file": "C:\\Clerici\\C#\\Progetti\\Test\\Quality control\\Ficep.RobServer\\Ficep.RobServer.MacroParser\\Data.cs", "source_location": "L75", "receiver": null}, {"caller_nid": "ficep_robserver_macroparser_data_mat_createdatalines", "callee": "Add", "is_member_call": true, "source_file": "C:\\Clerici\\C#\\Progetti\\Test\\Quality control\\Ficep.RobServer\\Ficep.RobServer.MacroParser\\Data.cs", "source_location": "L80", "receiver": null}, {"caller_nid": "ficep_robserver_macroparser_data_pcs_createdatalines", "callee": "Match", "is_member_call": true, "source_file": "C:\\Clerici\\C#\\Progetti\\Test\\Quality control\\Ficep.RobServer\\Ficep.RobServer.MacroParser\\Data.cs", "source_location": "L127", "receiver": null}, {"caller_nid": "ficep_robserver_macroparser_data_pcs_createdatalines", "callee": "First", "is_member_call": true, "source_file": "C:\\Clerici\\C#\\Progetti\\Test\\Quality control\\Ficep.RobServer\\Ficep.RobServer.MacroParser\\Data.cs", "source_location": "L127", "receiver": null}, {"caller_nid": "ficep_robserver_macroparser_data_pcs_createdatalines", "callee": "Split", "is_member_call": true, "source_file": "C:\\Clerici\\C#\\Progetti\\Test\\Quality control\\Ficep.RobServer\\Ficep.RobServer.MacroParser\\Data.cs", "source_location": "L127", "receiver": null}, {"caller_nid": "ficep_robserver_macroparser_data_pcs_createdatalines", "callee": "IsMatch", "is_member_call": true, "source_file": "C:\\Clerici\\C#\\Progetti\\Test\\Quality control\\Ficep.RobServer\\Ficep.RobServer.MacroParser\\Data.cs", "source_location": "L134", "receiver": null}, {"caller_nid": "ficep_robserver_macroparser_data_pcs_createdatalines", "callee": "First", "is_member_call": true, "source_file": "C:\\Clerici\\C#\\Progetti\\Test\\Quality control\\Ficep.RobServer\\Ficep.RobServer.MacroParser\\Data.cs", "source_location": "L134", "receiver": null}, {"caller_nid": "ficep_robserver_macroparser_data_pcs_createdatalines", "callee": "Split", "is_member_call": true, "source_file": "C:\\Clerici\\C#\\Progetti\\Test\\Quality control\\Ficep.RobServer\\Ficep.RobServer.MacroParser\\Data.cs", "source_location": "L134", "receiver": null}, {"caller_nid": "ficep_robserver_macroparser_data_pcs_createdatalines", "callee": "Add", "is_member_call": true, "source_file": "C:\\Clerici\\C#\\Progetti\\Test\\Quality control\\Ficep.RobServer\\Ficep.RobServer.MacroParser\\Data.cs", "source_location": "L137", "receiver": null}, {"caller_nid": "ficep_robserver_macroparser_data_pcs_createdatalines", "callee": "Add", "is_member_call": true, "source_file": "C:\\Clerici\\C#\\Progetti\\Test\\Quality control\\Ficep.RobServer\\Ficep.RobServer.MacroParser\\Data.cs", "source_location": "L139", "receiver": null}, {"caller_nid": "ficep_robserver_macroparser_data_pcs_createdatalines", "callee": "Add", "is_member_call": true, "source_file": "C:\\Clerici\\C#\\Progetti\\Test\\Quality control\\Ficep.RobServer\\Ficep.RobServer.MacroParser\\Data.cs", "source_location": "L141", "receiver": null}, {"caller_nid": "ficep_robserver_macroparser_data_pcs_createdatalines", "callee": "Add", "is_member_call": true, "source_file": "C:\\Clerici\\C#\\Progetti\\Test\\Quality control\\Ficep.RobServer\\Ficep.RobServer.MacroParser\\Data.cs", "source_location": "L143", "receiver": null}, {"caller_nid": "ficep_robserver_macroparser_data_pcs_createdatalines", "callee": "Add", "is_member_call": true, "source_file": "C:\\Clerici\\C#\\Progetti\\Test\\Quality control\\Ficep.RobServer\\Ficep.RobServer.MacroParser\\Data.cs", "source_location": "L145", "receiver": null}, {"caller_nid": "ficep_robserver_macroparser_data_pcs_createdatalines", "callee": "Add", "is_member_call": true, "source_file": "C:\\Clerici\\C#\\Progetti\\Test\\Quality control\\Ficep.RobServer\\Ficep.RobServer.MacroParser\\Data.cs", "source_location": "L147", "receiver": null}, {"caller_nid": "ficep_robserver_macroparser_data_pcs_createdatalines", "callee": "IsMatch", "is_member_call": true, "source_file": "C:\\Clerici\\C#\\Progetti\\Test\\Quality control\\Ficep.RobServer\\Ficep.RobServer.MacroParser\\Data.cs", "source_location": "L162", "receiver": null}, {"caller_nid": "ficep_robserver_macroparser_data_pcs_createdatalines", "callee": "First", "is_member_call": true, "source_file": "C:\\Clerici\\C#\\Progetti\\Test\\Quality control\\Ficep.RobServer\\Ficep.RobServer.MacroParser\\Data.cs", "source_location": "L162", "receiver": null}, {"caller_nid": "ficep_robserver_macroparser_data_pcs_createdatalines", "callee": "Split", "is_member_call": true, "source_file": "C:\\Clerici\\C#\\Progetti\\Test\\Quality control\\Ficep.RobServer\\Ficep.RobServer.MacroParser\\Data.cs", "source_location": "L162", "receiver": null}, {"caller_nid": "ficep_robserver_macroparser_data_pcs_createdatalines", "callee": "Add", "is_member_call": true, "source_file": "C:\\Clerici\\C#\\Progetti\\Test\\Quality control\\Ficep.RobServer\\Ficep.RobServer.MacroParser\\Data.cs", "source_location": "L165", "receiver": null}, {"caller_nid": "ficep_robserver_macroparser_data_pcs_createdatalines", "callee": "Add", "is_member_call": true, "source_file": "C:\\Clerici\\C#\\Progetti\\Test\\Quality control\\Ficep.RobServer\\Ficep.RobServer.MacroParser\\Data.cs", "source_location": "L167", "receiver": null}, {"caller_nid": "ficep_robserver_macroparser_data_pcs_createdatalines", "callee": "Add", "is_member_call": true, "source_file": "C:\\Clerici\\C#\\Progetti\\Test\\Quality control\\Ficep.RobServer\\Ficep.RobServer.MacroParser\\Data.cs", "source_location": "L169", "receiver": null}, {"caller_nid": "ficep_robserver_macroparser_data_pcs_createdatalines", "callee": "Add", "is_member_call": true, "source_file": "C:\\Clerici\\C#\\Progetti\\Test\\Quality control\\Ficep.RobServer\\Ficep.RobServer.MacroParser\\Data.cs", "source_location": "L171", "receiver": null}, {"caller_nid": "ficep_robserver_macroparser_data_pcs_createdatalines", "callee": "Add", "is_member_call": true, "source_file": "C:\\Clerici\\C#\\Progetti\\Test\\Quality control\\Ficep.RobServer\\Ficep.RobServer.MacroParser\\Data.cs", "source_location": "L173", "receiver": null}, {"caller_nid": "ficep_robserver_macroparser_data_pcs_createdatalines", "callee": "Add", "is_member_call": true, "source_file": "C:\\Clerici\\C#\\Progetti\\Test\\Quality control\\Ficep.RobServer\\Ficep.RobServer.MacroParser\\Data.cs", "source_location": "L175", "receiver": null}, {"caller_nid": "ficep_robserver_macroparser_data_pcs_createdatalines", "callee": "Match", "is_member_call": true, "source_file": "C:\\Clerici\\C#\\Progetti\\Test\\Quality control\\Ficep.RobServer\\Ficep.RobServer.MacroParser\\Data.cs", "source_location": "L182", "receiver": null}, {"caller_nid": "ficep_robserver_macroparser_data_pcs_createdatalines", "callee": "First", "is_member_call": true, "source_file": "C:\\Clerici\\C#\\Progetti\\Test\\Quality control\\Ficep.RobServer\\Ficep.RobServer.MacroParser\\Data.cs", "source_location": "L182", "receiver": null}, {"caller_nid": "ficep_robserver_macroparser_data_pcs_createdatalines", "callee": "Split", "is_member_call": true, "source_file": "C:\\Clerici\\C#\\Progetti\\Test\\Quality control\\Ficep.RobServer\\Ficep.RobServer.MacroParser\\Data.cs", "source_location": "L182", "receiver": null}, {"caller_nid": "ficep_robserver_macroparser_data_pcs_createdatalines", "callee": "Add", "is_member_call": true, "source_file": "C:\\Clerici\\C#\\Progetti\\Test\\Quality control\\Ficep.RobServer\\Ficep.RobServer.MacroParser\\Data.cs", "source_location": "L187", "receiver": null}, {"caller_nid": "ficep_robserver_macroparser_data_pcs_createdatalines", "callee": "Add", "is_member_call": true, "source_file": "C:\\Clerici\\C#\\Progetti\\Test\\Quality control\\Ficep.RobServer\\Ficep.RobServer.MacroParser\\Data.cs", "source_location": "L189", "receiver": null}, {"caller_nid": "ficep_robserver_macroparser_data_pcs_createdatalines", "callee": "Add", "is_member_call": true, "source_file": "C:\\Clerici\\C#\\Progetti\\Test\\Quality control\\Ficep.RobServer\\Ficep.RobServer.MacroParser\\Data.cs", "source_location": "L191", "receiver": null}, {"caller_nid": "ficep_robserver_macroparser_data_pcs_createdatalines", "callee": "Add", "is_member_call": true, "source_file": "C:\\Clerici\\C#\\Progetti\\Test\\Quality control\\Ficep.RobServer\\Ficep.RobServer.MacroParser\\Data.cs", "source_location": "L193", "receiver": null}, {"caller_nid": "ficep_robserver_macroparser_data_pcs_createdatalines", "callee": "Add", "is_member_call": true, "source_file": "C:\\Clerici\\C#\\Progetti\\Test\\Quality control\\Ficep.RobServer\\Ficep.RobServer.MacroParser\\Data.cs", "source_location": "L195", "receiver": null}, {"caller_nid": "ficep_robserver_macroparser_data_pcs_createdatalines", "callee": "Add", "is_member_call": true, "source_file": "C:\\Clerici\\C#\\Progetti\\Test\\Quality control\\Ficep.RobServer\\Ficep.RobServer.MacroParser\\Data.cs", "source_location": "L197", "receiver": null}, {"caller_nid": "ficep_robserver_macroparser_data_prf_createdatalines", "callee": "Match", "is_member_call": true, "source_file": "C:\\Clerici\\C#\\Progetti\\Test\\Quality control\\Ficep.RobServer\\Ficep.RobServer.MacroParser\\Data.cs", "source_location": "L244", "receiver": null}, {"caller_nid": "ficep_robserver_macroparser_data_prf_createdatalines", "callee": "First", "is_member_call": true, "source_file": "C:\\Clerici\\C#\\Progetti\\Test\\Quality control\\Ficep.RobServer\\Ficep.RobServer.MacroParser\\Data.cs", "source_location": "L244", "receiver": null}, {"caller_nid": "ficep_robserver_macroparser_data_prf_createdatalines", "callee": "Split", "is_member_call": true, "source_file": "C:\\Clerici\\C#\\Progetti\\Test\\Quality control\\Ficep.RobServer\\Ficep.RobServer.MacroParser\\Data.cs", "source_location": "L244", "receiver": null}, {"caller_nid": "ficep_robserver_macroparser_data_prf_createdatalines", "callee": "IsMatch", "is_member_call": true, "source_file": "C:\\Clerici\\C#\\Progetti\\Test\\Quality control\\Ficep.RobServer\\Ficep.RobServer.MacroParser\\Data.cs", "source_location": "L248", "receiver": null}, {"caller_nid": "ficep_robserver_macroparser_data_prf_createdatalines", "callee": "First", "is_member_call": true, "source_file": "C:\\Clerici\\C#\\Progetti\\Test\\Quality control\\Ficep.RobServer\\Ficep.RobServer.MacroParser\\Data.cs", "source_location": "L248", "receiver": null}, {"caller_nid": "ficep_robserver_macroparser_data_prf_createdatalines", "callee": "Split", "is_member_call": true, "source_file": "C:\\Clerici\\C#\\Progetti\\Test\\Quality control\\Ficep.RobServer\\Ficep.RobServer.MacroParser\\Data.cs", "source_location": "L248", "receiver": null}, {"caller_nid": "ficep_robserver_macroparser_data_prf_createdatalines", "callee": "Add", "is_member_call": true, "source_file": "C:\\Clerici\\C#\\Progetti\\Test\\Quality control\\Ficep.RobServer\\Ficep.RobServer.MacroParser\\Data.cs", "source_location": "L251", "receiver": null}, {"caller_nid": "ficep_robserver_macroparser_data_prf_createdatalines", "callee": "IsMatch", "is_member_call": true, "source_file": "C:\\Clerici\\C#\\Progetti\\Test\\Quality control\\Ficep.RobServer\\Ficep.RobServer.MacroParser\\Data.cs", "source_location": "L260", "receiver": null}, {"caller_nid": "ficep_robserver_macroparser_data_prf_createdatalines", "callee": "First", "is_member_call": true, "source_file": "C:\\Clerici\\C#\\Progetti\\Test\\Quality control\\Ficep.RobServer\\Ficep.RobServer.MacroParser\\Data.cs", "source_location": "L260", "receiver": null}, {"caller_nid": "ficep_robserver_macroparser_data_prf_createdatalines", "callee": "Split", "is_member_call": true, "source_file": "C:\\Clerici\\C#\\Progetti\\Test\\Quality control\\Ficep.RobServer\\Ficep.RobServer.MacroParser\\Data.cs", "source_location": "L260", "receiver": null}, {"caller_nid": "ficep_robserver_macroparser_data_prf_createdatalines", "callee": "Add", "is_member_call": true, "source_file": "C:\\Clerici\\C#\\Progetti\\Test\\Quality control\\Ficep.RobServer\\Ficep.RobServer.MacroParser\\Data.cs", "source_location": "L263", "receiver": null}, {"caller_nid": "ficep_robserver_macroparser_data_prf_createdatalines", "callee": "Match", "is_member_call": true, "source_file": "C:\\Clerici\\C#\\Progetti\\Test\\Quality control\\Ficep.RobServer\\Ficep.RobServer.MacroParser\\Data.cs", "source_location": "L269", "receiver": null}, {"caller_nid": "ficep_robserver_macroparser_data_prf_createdatalines", "callee": "First", "is_member_call": true, "source_file": "C:\\Clerici\\C#\\Progetti\\Test\\Quality control\\Ficep.RobServer\\Ficep.RobServer.MacroParser\\Data.cs", "source_location": "L269", "receiver": null}, {"caller_nid": "ficep_robserver_macroparser_data_prf_createdatalines", "callee": "Split", "is_member_call": true, "source_file": "C:\\Clerici\\C#\\Progetti\\Test\\Quality control\\Ficep.RobServer\\Ficep.RobServer.MacroParser\\Data.cs", "source_location": "L269", "receiver": null}, {"caller_nid": "ficep_robserver_macroparser_data_prf_createdatalines", "callee": "Add", "is_member_call": true, "source_file": "C:\\Clerici\\C#\\Progetti\\Test\\Quality control\\Ficep.RobServer\\Ficep.RobServer.MacroParser\\Data.cs", "source_location": "L274", "receiver": null}]}