{"nodes": [{"id": "c_clerici_c_progetti_test_quality_control_ficep_macrogra_ficep_macrogra_macro_esti46_cs", "label": "ESTI46.cs", "file_type": "code", "source_file": "Ficep.MacroGra/Ficep.MacroGra/MACRO/ESTI46.cs", "source_location": "L1"}, {"id": "macro_esti46_ficep_macrogra", "label": "Ficep.MacroGra", "file_type": "code", "source_file": "Ficep.MacroGra/Ficep.MacroGra/MACRO/ESTI46.cs", "source_location": "L8"}, {"id": "macro_esti46_esti46", "label": "ESTI46", "file_type": "code", "source_file": "Ficep.MacroGra/Ficep.MacroGra/MACRO/ESTI46.cs", "source_location": "L10"}, {"id": "eyemacro", "label": "EyeMacro", "file_type": "code", "source_file": "", "source_location": ""}, {"id": "macro_esti46_esti46_createmacro", "label": ".CreateMacro()", "file_type": "code", "source_file": "Ficep.MacroGra/Ficep.MacroGra/MACRO/ESTI46.cs", "source_location": "L19"}], "edges": [{"source": "c_clerici_c_progetti_test_quality_control_ficep_macrogra_ficep_macrogra_macro_esti46_cs", "target": "utility3d", "relation": "imports", "context": "import", "confidence": "EXTRACTED", "source_file": "Ficep.MacroGra/Ficep.MacroGra/MACRO/ESTI46.cs", "source_location": "L2", "weight": 1.0}, {"source": "c_clerici_c_progetti_test_quality_control_ficep_macrogra_ficep_macrogra_macro_esti46_cs", "target": "data", "relation": "imports", "context": "import", "confidence": "EXTRACTED", "source_file": "Ficep.MacroGra/Ficep.MacroGra/MACRO/ESTI46.cs", "source_location": "L3", "weight": 1.0}, {"source": "c_clerici_c_progetti_test_quality_control_ficep_macrogra_ficep_macrogra_macro_esti46_cs", "target": "entities", "relation": "imports", "context": "import", "confidence": "EXTRACTED", "source_file": "Ficep.MacroGra/Ficep.MacroGra/MACRO/ESTI46.cs", "source_location": "L4", "weight": 1.0}, {"source": "c_clerici_c_progetti_test_quality_control_ficep_macrogra_ficep_macrogra_macro_esti46_cs", "target": "geometry", "relation": "imports", "context": "import", "confidence": "EXTRACTED", "source_file": "Ficep.MacroGra/Ficep.MacroGra/MACRO/ESTI46.cs", "source_location": "L5", "weight": 1.0}, {"source": "c_clerici_c_progetti_test_quality_control_ficep_macrogra_ficep_macrogra_macro_esti46_cs", "target": "generic", "relation": "imports", "context": "import", "confidence": "EXTRACTED", "source_file": "Ficep.MacroGra/Ficep.MacroGra/MACRO/ESTI46.cs", "source_location": "L6", "weight": 1.0}, {"source": "c_clerici_c_progetti_test_quality_control_ficep_macrogra_ficep_macrogra_macro_esti46_cs", "target": "macro_esti46_ficep_macrogra", "relation": "contains", "confidence": "EXTRACTED", "source_file": "Ficep.MacroGra/Ficep.MacroGra/MACRO/ESTI46.cs", "source_location": "L8", "weight": 1.0}, {"source": "c_clerici_c_progetti_test_quality_control_ficep_macrogra_ficep_macrogra_macro_esti46_cs", "target": "macro_esti46_esti46", "relation": "contains", "confidence": "EXTRACTED", "source_file": "Ficep.MacroGra/Ficep.MacroGra/MACRO/ESTI46.cs", "source_location": "L10", "weight": 1.0}, {"source": "macro_esti46_esti46", "target": "eyemacro", "relation": "inherits", "confidence": "EXTRACTED", "source_file": "Ficep.MacroGra/Ficep.MacroGra/MACRO/ESTI46.cs", "source_location": "L10", "weight": 1.0}, {"source": "macro_esti46_esti46", "target": "macro_esti46_esti46_createmacro", "relation": "method", "confidence": "EXTRACTED", "source_file": "Ficep.MacroGra/Ficep.MacroGra/MACRO/ESTI46.cs", "source_location": "L19", "weight": 1.0}], "raw_calls": [{"caller_nid": "macro_esti46_esti46_createmacro", "callee": "Contains", "is_member_call": true, "source_file": "C:\\Clerici\\C#\\Progetti\\Test\\Quality control\\Ficep.MacroGra\\Ficep.MacroGra\\MACRO\\ESTI46.cs", "source_location": "L22", "receiver": null}, {"caller_nid": "macro_esti46_esti46_createmacro", "callee": "Validate", "is_member_call": false, "source_file": "C:\\Clerici\\C#\\Progetti\\Test\\Quality control\\Ficep.MacroGra\\Ficep.MacroGra\\MACRO\\ESTI46.cs", "source_location": "L26", "receiver": null}, {"caller_nid": "macro_esti46_esti46_createmacro", "callee": "Add", "is_member_call": true, "source_file": "C:\\Clerici\\C#\\Progetti\\Test\\Quality control\\Ficep.MacroGra\\Ficep.MacroGra\\MACRO\\ESTI46.cs", "source_location": "L33", "receiver": null}, {"caller_nid": "macro_esti46_esti46_createmacro", "callee": "Add", "is_member_call": true, "source_file": "C:\\Clerici\\C#\\Progetti\\Test\\Quality control\\Ficep.MacroGra\\Ficep.MacroGra\\MACRO\\ESTI46.cs", "source_location": "L35", "receiver": null}, {"caller_nid": "macro_esti46_esti46_createmacro", "callee": "Add", "is_member_call": true, "source_file": "C:\\Clerici\\C#\\Progetti\\Test\\Quality control\\Ficep.MacroGra\\Ficep.MacroGra\\MACRO\\ESTI46.cs", "source_location": "L37", "receiver": null}, {"caller_nid": "macro_esti46_esti46_createmacro", "callee": "Add", "is_member_call": true, "source_file": "C:\\Clerici\\C#\\Progetti\\Test\\Quality control\\Ficep.MacroGra\\Ficep.MacroGra\\MACRO\\ESTI46.cs", "source_location": "L39", "receiver": null}, {"caller_nid": "macro_esti46_esti46_createmacro", "callee": "Add", "is_member_call": true, "source_file": "C:\\Clerici\\C#\\Progetti\\Test\\Quality control\\Ficep.MacroGra\\Ficep.MacroGra\\MACRO\\ESTI46.cs", "source_location": "L41", "receiver": null}, {"caller_nid": "macro_esti46_esti46_createmacro", "callee": "Add", "is_member_call": true, "source_file": "C:\\Clerici\\C#\\Progetti\\Test\\Quality control\\Ficep.MacroGra\\Ficep.MacroGra\\MACRO\\ESTI46.cs", "source_location": "L43", "receiver": null}, {"caller_nid": "macro_esti46_esti46_createmacro", "callee": "GetSolidSubtractOffsetAmount", "is_member_call": true, "source_file": "C:\\Clerici\\C#\\Progetti\\Test\\Quality control\\Ficep.MacroGra\\Ficep.MacroGra\\MACRO\\ESTI46.cs", "source_location": "L52", "receiver": null}, {"caller_nid": "macro_esti46_esti46_createmacro", "callee": "SolidSubtract", "is_member_call": true, "source_file": "C:\\Clerici\\C#\\Progetti\\Test\\Quality control\\Ficep.MacroGra\\Ficep.MacroGra\\MACRO\\ESTI46.cs", "source_location": "L53", "receiver": null}, {"caller_nid": "macro_esti46_esti46_createmacro", "callee": "Add", "is_member_call": true, "source_file": "C:\\Clerici\\C#\\Progetti\\Test\\Quality control\\Ficep.MacroGra\\Ficep.MacroGra\\MACRO\\ESTI46.cs", "source_location": "L56", "receiver": null}]}